truthpy/Document.py
truthpy/GTElement.py
truthpy/Rect.py
truthpy/Table.py
truthpy/__init__.py
truthpy-1.1.dist-info/METADATA
truthpy-1.1.dist-info/WHEEL
truthpy-1.1.dist-info/top_level.txt
truthpy-1.1.dist-info/RECORD
